regularizeddiscriminantanalysis/__init__.py
regularizeddiscriminantanalysis/classifier.py
regularizeddiscriminantanalysis-0.1.1.dist-info/licenses/LICENSE
regularizeddiscriminantanalysis-0.1.1.dist-info/METADATA
regularizeddiscriminantanalysis-0.1.1.dist-info/WHEEL
regularizeddiscriminantanalysis-0.1.1.dist-info/top_level.txt
regularizeddiscriminantanalysis-0.1.1.dist-info/RECORD
