Metadata-Version: 2.4
Name: RegularizedDiscriminantAnalysis
Version: 0.1.1
Summary: A scikit-learn compatible implementation of Regularized Discriminant Analysis (RDA)
Author-email: Federico Clerici <fez.cle@gmail.com>, Raffaele D'Agostino <raffaeledagostino11@gmail.com>
License-Expression: MIT
Project-URL: Homepage, https://github.com/F3z11/RDA_implementation
Project-URL: Bug Tracker, https://github.com/F3z11/RDA_implementation/issues
Keywords: machine learning,classification,discriminant analysis,RDA,LDA,QDA,scikit-learn
Classifier: Development Status :: 4 - Beta
Classifier: Intended Audience :: Science/Research
Classifier: Intended Audience :: Developers
Classifier: Topic :: Scientific/Engineering :: Artificial Intelligence
Classifier: Programming Language :: Python :: 3
Classifier: Programming Language :: Python :: 3.8
Classifier: Programming Language :: Python :: 3.9
Classifier: Programming Language :: Python :: 3.10
Classifier: Programming Language :: Python :: 3.11
Classifier: Programming Language :: Python :: 3.12
Classifier: Operating System :: OS Independent
Requires-Python: >=3.8
License-File: LICENSE
Requires-Dist: numpy>=1.20
Requires-Dist: scipy>=1.7
Requires-Dist: scikit-learn>=1.0
Dynamic: license-file
